ippserver/__init__.py
ippserver/__main__.py
ippserver/behaviour.py
ippserver/constants.py
ippserver/parsers.py
ippserver/pc2paper.py
ippserver/ppd.py
ippserver/request.py
ippserver/server.py
ippserver/data/404.txt
ippserver/data/error.txt
ippserver/data/homepage.txt
ippserver-0.2.dist-info/METADATA
ippserver-0.2.dist-info/RECORD
ippserver-0.2.dist-info/WHEEL
ippserver-0.2.dist-info/entry_points.txt
ippserver-0.2.dist-info/top_level.txt
